h5_to_edf/__init__.py
h5_to_edf/blisstomo_reader.py
h5_to_edf/converter.py
h5_to_edf/converter_oven.py
h5_to_edf/current_reader.py
h5_to_edf/edf_file_series.py
h5_to_edf/exceptions.py
h5_to_edf/info_output.py
h5_to_edf/report_output.py
h5_to_edf/xml_output.py
h5_to_edf/yaml.py
h5_to_edf/yaml_output.py
h5_to_edf/app/__init__.py
h5_to_edf/app/h5_to_edf.py
h5_to_edf-1.5.3.dist-info/METADATA
h5_to_edf-1.5.3.dist-info/WHEEL
h5_to_edf-1.5.3.dist-info/entry_points.txt
h5_to_edf-1.5.3.dist-info/top_level.txt
h5_to_edf-1.5.3.dist-info/RECORD
