Metadata-Version: 2.1
Name: h5_to_edf
Version: 1.5.3
Summary: Convert a HDF5 file to EDF files
Author-email: Jibril MAMMERI <mammeri@esrf.fr>
License: MIT
Project-URL: Homepage, https://gitlab.esrf.fr/tomo/h5_to_edf
Project-URL: Bug Tracker, https://gitlab.esrf.fr/tomo/h5_to_edf/issues
Classifier: Programming Language :: Python :: 3
Classifier: License :: OSI Approved :: MIT License
Classifier: Operating System :: OS Independent
Requires-Python: >=3.8
Requires-Dist: h5py
Requires-Dist: fabio
Requires-Dist: hdf5plugin
Requires-Dist: pyyaml
Provides-Extra: dev
Requires-Dist: black; extra == "dev"
Requires-Dist: pytest; extra == "dev"
Requires-Dist: types-PyYAML; extra == "dev"
